hello.py
snifhex-0.1.1.dist-info/LICENSE.txt
snifhex-0.1.1.dist-info/METADATA
snifhex-0.1.1.dist-info/WHEEL
snifhex-0.1.1.dist-info/top_level.txt
snifhex-0.1.1.dist-info/RECORD
