Metadata-Version: 2.1
Name: snifhex
Version: 0.1.1
Summary: collection of scripts made by snifhex.
Home-page: UNKNOWN
Author: UNKNOWN
Author-email: UNKNOWN
License: UNKNOWN
Platform: UNKNOWN
